bert_summarizer/__init__.py
bert_summarizer/config/__init__.py
bert_summarizer/config/bertsum.py
bert_summarizer/data/__init__.py
bert_summarizer/data/data_collator.py
bert_summarizer/data/datasets/__init__.py
bert_summarizer/data/datasets/bertsum.py
bert_summarizer/models/__init__.py
bert_summarizer/models/bertsum/__init__.py
bert_summarizer/models/bertsum/abs/__init__.py
bert_summarizer/models/bertsum/abs/abs.py
bert_summarizer/models/bertsum/abs/decoder.py
bert_summarizer/models/bertsum/abs/onmt_decoder.py
bert_summarizer/models/bertsum/ext.py
bert_summarizer/models/embeddings.py
bert_summarizer/models/loss.py
bert_summarizer/tokenizers/__init__.py
bert_summarizer/tokenizers/bertsum.py
bert_summarizer/trainers/__init__.py
bert_summarizer/trainers/encoder_decoder.py
bert_summarizer/trainers/lr_lambda.py
bert_summarizer/utils/__init__.py
bert_summarizer/utils/bertsum.py
bert_summarizer/utils/common.py
bert_summarizer/utils/nn.py
bert_summarizer-0.2.5.dist-info/LICENSE
bert_summarizer-0.2.5.dist-info/WHEEL
bert_summarizer-0.2.5.dist-info/METADATA
bert_summarizer-0.2.5.dist-info/RECORD
