Metadata-Version: 2.1
Name: bert-summarizer
Version: 0.2.5
Summary: Text Summarization Library based on transformers
Home-page: https://github.com/k-tahiro/bert-summarizer
License: MIT
Keywords: BERT,Text Summarization
Author: k-tahiro
Author-email: tahiro.k.ad@gmail.com
Requires-Python: >=3.6.2,<3.9
Classifier: License :: OSI Approved :: MIT License
Classifier: Programming Language :: Python :: 3
Classifier: Programming Language :: Python :: 3.7
Classifier: Programming Language :: Python :: 3.8
Provides-Extra: onmt
Requires-Dist: OpenNMT-py (>=2.0.1); extra == "onmt"
Requires-Dist: ginza (>=4.0.5,<5.0.0)
Requires-Dist: transformers[torch,ja] (>=4.0.0)
Project-URL: Repository, https://github.com/k-tahiro/bert-summarizer
